jupyterhub_moss/__init__.py
jupyterhub_moss/batch_script.sh
jupyterhub_moss/models.py
jupyterhub_moss/spawner.py
jupyterhub_moss/utils.py
jupyterhub_moss/form/option_form.css
jupyterhub_moss/form/option_form.js
jupyterhub_moss/templates/option_form.html
jupyterhub_moss-10.0.0.dist-info/licenses/LICENSE
jupyterhub_moss-10.0.0.dist-info/METADATA
jupyterhub_moss-10.0.0.dist-info/WHEEL
jupyterhub_moss-10.0.0.dist-info/top_level.txt
jupyterhub_moss-10.0.0.dist-info/RECORD
