Metadata-Version: 2.4
Name: jupyterhub_moss
Version: 10.0.0
Summary: JupyterHub SLURM Spawner with specific spawn page
Author-email: European Synchrotron Radiation Facility <jupyter@esrf.fr>
License-Expression: MIT
Project-URL: Homepage, https://github.com/silx-kit/jupyterhub_moss
Project-URL: Repository, https://github.com/silx-kit/jupyterhub_moss
Project-URL: Issues, https://github.com/silx-kit/jupyterhub_moss/issues
Project-URL: Changelog, https://github.com/silx-kit/jupyterhub_moss/releases
Keywords: jupyterhub,slurm
Classifier: Development Status :: 5 - Production/Stable
Classifier: Environment :: Web Environment
Classifier: Framework :: Jupyter
Classifier: Operating System :: POSIX :: Linux
Classifier: Programming Language :: Python :: 3
Classifier: Programming Language :: JavaScript
Requires-Python: >=3.10
License-File: LICENSE
Requires-Dist: batchspawner>=1.0
Requires-Dist: jinja2
Requires-Dist: jupyterhub>=5.0.0
Requires-Dist: pydantic<3,>=2.4.0
Requires-Dist: traitlets
Provides-Extra: dev
Requires-Dist: bandit; extra == "dev"
Requires-Dist: black; extra == "dev"
Requires-Dist: build; extra == "dev"
Requires-Dist: bump2version; extra == "dev"
Requires-Dist: check-manifest; extra == "dev"
Requires-Dist: flake8; extra == "dev"
Requires-Dist: isort; extra == "dev"
Requires-Dist: jupyter_server; extra == "dev"
Requires-Dist: mypy; extra == "dev"
Requires-Dist: pytest; extra == "dev"
Requires-Dist: pytest-asyncio<0.23,>=0.17; extra == "dev"
Requires-Dist: twine; extra == "dev"
Dynamic: license-file
